README.rst
setup.py
rio_pansharpen/__init__.py
rio_pansharpen/methods.py
rio_pansharpen/utils.py
rio_pansharpen/worker.py
rio_pansharpen.egg-info/PKG-INFO
rio_pansharpen.egg-info/SOURCES.txt
rio_pansharpen.egg-info/dependency_links.txt
rio_pansharpen.egg-info/entry_points.txt
rio_pansharpen.egg-info/not-zip-safe
rio_pansharpen.egg-info/requires.txt
rio_pansharpen.egg-info/top_level.txt
rio_pansharpen/scripts/__init__.py
rio_pansharpen/scripts/cli.py