Metadata-Version: 1.0
Name: rio-pansharpen
Version: 0.2.0
Summary: rio-pansharpen
Home-page: https://github.com/mapbox/rio-pansharpen
Author: Virginia Ng
Author-email: virginia@mapbox.com
License: MIT
Platform: UNKNOWN
